ibm_watsonx_gov/__init__.py
ibm_watsonx_gov/agent_catalog/__init__.py
ibm_watsonx_gov/agent_catalog/clients/__init__.py
ibm_watsonx_gov/agent_catalog/clients/ai_agent_client.py
ibm_watsonx_gov/agent_catalog/core/__init__.py
ibm_watsonx_gov/agent_catalog/core/agent_loader.py
ibm_watsonx_gov/agent_catalog/core/agents.py
ibm_watsonx_gov/agent_catalog/entities/__init__.py
ibm_watsonx_gov/agent_catalog/entities/ai_agent.py
ibm_watsonx_gov/agent_catalog/utils/__init__.py
ibm_watsonx_gov/agent_catalog/utils/constants.py
ibm_watsonx_gov/agent_catalog/utils/notebook_utils.py
ibm_watsonx_gov/ai_experiments/__init__.py
ibm_watsonx_gov/ai_experiments/ai_experiments_client.py
ibm_watsonx_gov/ai_experiments/utils/__init__.py
ibm_watsonx_gov/ai_experiments/utils/ai_experiment_utils.py
ibm_watsonx_gov/clients/__init__.py
ibm_watsonx_gov/clients/api_client.py
ibm_watsonx_gov/clients/segment_client.py
ibm_watsonx_gov/clients/usage_client.cpython-312-x86_64-linux-gnu.so
ibm_watsonx_gov/clients/wx_ai_client.py
ibm_watsonx_gov/config/__init__.py
ibm_watsonx_gov/config/agentic_ai_configuration.py
ibm_watsonx_gov/config/gen_ai_configuration.py
ibm_watsonx_gov/config/model_risk_configuration.py
ibm_watsonx_gov/config/predictive_ai_configuration.py
ibm_watsonx_gov/entities/__init__.py
ibm_watsonx_gov/entities/agentic_app.py
ibm_watsonx_gov/entities/agentic_evaluation_result.py
ibm_watsonx_gov/entities/ai_evaluation.py
ibm_watsonx_gov/entities/ai_experiment.py
ibm_watsonx_gov/entities/base_classes.py
ibm_watsonx_gov/entities/container.py
ibm_watsonx_gov/entities/credentials.py
ibm_watsonx_gov/entities/criteria.py
ibm_watsonx_gov/entities/enums.py
ibm_watsonx_gov/entities/evaluation_result.py
ibm_watsonx_gov/entities/foundation_model.py
ibm_watsonx_gov/entities/llm_judge.py
ibm_watsonx_gov/entities/locale.py
ibm_watsonx_gov/entities/mapping.py
ibm_watsonx_gov/entities/metric.py
ibm_watsonx_gov/entities/metric_threshold.py
ibm_watsonx_gov-1.4.0.dist-info/METADATA
ibm_watsonx_gov-1.4.0.dist-info/WHEEL
ibm_watsonx_gov-1.4.0.dist-info/RECORD
